sheetscut/__init__.py
sheetscut/__main__.py
sheetscut/cli.py
sheetscut/core.py
sheetscut/matcher.py
sheetscut/transcript.py
sheetscut/utils.py
sheetscut/xml_generator.py
sheetscut-0.1.0.dist-info/METADATA
sheetscut-0.1.0.dist-info/WHEEL
sheetscut-0.1.0.dist-info/entry_points.txt
sheetscut-0.1.0.dist-info/licenses/LICENSE
sheetscut-0.1.0.dist-info/RECORD
