Metadata-Version: 2.4
Name: sheetscut
Version: 0.1.0
Summary: Producer paper edit to Premiere Pro sequence generator
Project-URL: Homepage, https://github.com/mrescandon/sheetscut
Project-URL: Repository, https://github.com/mrescandon/sheetscut
Project-URL: Issues, https://github.com/mrescandon/sheetscut/issues
Author-email: Paul Escandon <paul@mediapending.net>
License-Expression: MIT
License-File: LICENSE
Keywords: editing,fcp,premiere,transcription,video,xml
Classifier: Development Status :: 4 - Beta
Classifier: Intended Audience :: End Users/Desktop
Classifier: License :: OSI Approved :: MIT License
Classifier: Operating System :: OS Independent
Classifier: Programming Language :: Python :: 3
Classifier: Programming Language :: Python :: 3.9
Classifier: Programming Language :: Python :: 3.10
Classifier: Programming Language :: Python :: 3.11
Classifier: Programming Language :: Python :: 3.12
Classifier: Topic :: Multimedia :: Video
Requires-Python: >=3.9
Provides-Extra: dev
Requires-Dist: pytest>=7.0; extra == 'dev'
Requires-Dist: ruff>=0.1.0; extra == 'dev'
